example_package_ccalafiore/__init__.py
example_package_ccalafiore/module_a.py
example_package_ccalafiore/module_b/__init__.py
example_package_ccalafiore/module_b/module_b_1.py
example_package_ccalafiore/module_b/module_b_2.py
example_package_ccalafiore-0.0.1.dist-info/METADATA
example_package_ccalafiore-0.0.1.dist-info/WHEEL
example_package_ccalafiore-0.0.1.dist-info/licenses/LICENSE
example_package_ccalafiore-0.0.1.dist-info/RECORD
