Metadata-Version: 2.4
Name: example_package_ccalafiore
Version: 0.0.1
Summary: A small example package
Project-URL: Homepage, https://www.google.com
Project-URL: Repository, https://github.com/ccalafiore/CalaPy
Project-URL: Issues, https://github.com/ccalafiore/CalaPy/issues
Author-email: Example Author <author@example.com>
License-Expression: MIT
License-File: LICENSE
Classifier: Operating System :: OS Independent
Classifier: Programming Language :: Python :: 3
Requires-Python: >=3.9
Requires-Dist: numpy
Requires-Dist: pandas
